watchyourlanclient/__init__.py
watchyourlanclient-2024.1009a0.dist-info/LICENSE
watchyourlanclient-2024.1009a0.dist-info/METADATA
watchyourlanclient-2024.1009a0.dist-info/WHEEL
watchyourlanclient-2024.1009a0.dist-info/top_level.txt
watchyourlanclient-2024.1009a0.dist-info/RECORD
