Metadata-Version: 2.1
Name: watchyourlanclient
Version: 2024.1009a0
Summary: Python client to talk to WatchYourLAN APIs
Home-page: https://github.com/drwahl/py-watchyourlanclient
Author: David Wahlstrom
Author-email: David Wahlstrom <david.wahlstrom@gmail.com>
License: Apache License
Project-URL: Homepage, https://github.com/drwahl/py-watchyourlanclient
Keywords: watchyourlan
Classifier: License :: OSI Approved :: MIT License
Classifier: Programming Language :: Python
Classifier: Programming Language :: Python :: 3
Requires-Python: >=3.11
License-File: LICENSE
Requires-Dist: cachetools>=5.5.0
Requires-Dist: httpx>=0.27.0
Provides-Extra: dev
Requires-Dist: pip-tools; extra == "dev"
Requires-Dist: pytest; extra == "dev"
Requires-Dist: autopep8; extra == "dev"
Requires-Dist: ipdb; extra == "dev"
Requires-Dist: pytest-asyncio; extra == "dev"
Requires-Dist: build; extra == "dev"
Requires-Dist: twine; extra == "dev"
Requires-Dist: bumpver; extra == "dev"
